aiotraq_message/__init__.py
aiotraq_message/engine.py
aiotraq_message/manager.py
aiotraq_message/message.py
aiotraq_message/py.typed
aiotraq_message/utils.py
aiotraq_message-0.2.5.dist-info/METADATA
aiotraq_message-0.2.5.dist-info/WHEEL
aiotraq_message-0.2.5.dist-info/RECORD
