Metadata-Version: 2.1
Name: aiotraq-message
Version: 0.2.5
Summary: aiotraq Plugin that supports interactive message sending using Streamlit-style syntax for traQ
Home-page: https://github.com/toshi-pono/aiotraq
License: MIT
Keywords: traQ,bot,message,aiotraq
Author: toshi00
Requires-Python: >=3.10,<4.0
Classifier: License :: OSI Approved :: MIT License
Classifier: Programming Language :: Python :: 3
Classifier: Programming Language :: Python :: 3.10
Classifier: Programming Language :: Python :: 3.11
Classifier: Programming Language :: Python :: 3.12
Requires-Dist: aiotraq (>=0.1.2,<0.3.0)
Requires-Dist: aiotraq-bot (>=0.1.2,<0.3.0)
Requires-Dist: numpy (>=1.26.4,<2.0.0)
Requires-Dist: pandas (>=2.2.2,<3.0.0)
Requires-Dist: pillow (>=10.3.0,<11.0.0)
Requires-Dist: tabulate (>=0.9.0,<0.10.0)
Project-URL: Repository, https://github.com/toshi-pono/aiotraq
Project-URL: Source Code, https://github.com/toshi-pono/aiotraq/tree/main/libs/message
